hybrid_rsa_aes/__init__.py
hybrid_rsa_aes/cipher.py
hybrid_rsa_aes/version.py
tests/__init__.py
tests/test_cipher.py
hybrid_rsa_aes-0.5.0.dist-info/LICENSE
hybrid_rsa_aes-0.5.0.dist-info/METADATA
hybrid_rsa_aes-0.5.0.dist-info/WHEEL
hybrid_rsa_aes-0.5.0.dist-info/top_level.txt
hybrid_rsa_aes-0.5.0.dist-info/RECORD
